dian_person_rut_status/__init__.py
dian_person_rut_status/custom_types.py
dian_person_rut_status/exceptions.py
dian_person_rut_status/muisca.py
dian_person_rut_status/utils.py
dian_person_rut_status-0.1.10.dist-info/LICENSE
dian_person_rut_status-0.1.10.dist-info/METADATA
dian_person_rut_status-0.1.10.dist-info/WHEEL
dian_person_rut_status-0.1.10.dist-info/RECORD
